penguinpi/__init__.py
penguinpi-1.0.0.dist-info/LICENSE
penguinpi-1.0.0.dist-info/METADATA
penguinpi-1.0.0.dist-info/WHEEL
penguinpi-1.0.0.dist-info/top_level.txt
penguinpi-1.0.0.dist-info/RECORD
