Metadata-Version: 2.1
Name: penguinpi
Version: 1.0.0
Summary: Library for communicating with and controlling the PenguinPi robot platform.
Home-page: https://github.com/cirrus-robotics/penguinpi
Author: Cirrus Robotics Pty Ltd
License: MIT
Project-URL: Documentation, https://github.com/cirrus-robotics/penguinpi/README.md
Project-URL: Issue tracker, https://github.com/cirrus-robotics/penguinpi/issues
Platform: UNKNOWN
Classifier: License :: OSI Approved :: MIT License
Classifier: Intended Audience :: Developers
Classifier: Natural Language :: English
Classifier: Operating System :: OS Independent
Classifier: Programming Language :: Python :: 2.7
Classifier: Programming Language :: Python :: 3.5
Classifier: Programming Language :: Python :: 3.6
Classifier: Programming Language :: Python :: 3.7
Classifier: Programming Language :: Python :: 3.8
Classifier: Topic :: Internet
Classifier: Topic :: Software Development :: Libraries
Classifier: Topic :: Software Development :: Libraries :: Python Modules
Classifier: Topic :: Utilities
Requires-Python: >=2.7
Requires-Dist: requests
Requires-Dist: opencv-python
Requires-Dist: numpy
